{
  "name": "calico-vxlan",
  "type": "clab",
  "clab": {
    "config": {
      "prefix": "clab",
      "mgmt": {
        "network": "clab",
        "bridge": "br-34417ee0e937",
        "ipv4-subnet": "172.20.20.0/24",
        "ipv4-gw": "172.20.20.1",
        "ipv6-subnet": "3fff:172:20:20::/64",
        "ipv6-gw": "3fff:172:20:20::1",
        "mtu": 1500,
        "external-access": true
      }
    }
  },
  "ssh-pub-keys": [],
  "nodes": {
    "host-external": {
      "index": "0",
      "shortname": "host-external",
      "longname": "clab-calico-vxlan-host-external",
      "fqdn": "host-external.calico-vxlan.io",
      "group": "",
      "labdir": "/media/sf_Cilium/containerlab/clab-calico-vxlan/host-external",
      "kind": "linux",
      "image": "curlimages/curl:8.1.2",
      "mgmt-net": "",
      "mgmt-intf": "",
      "mgmt-ipv4-address": "172.20.20.3",
      "mgmt-ipv4-prefix-length": 24,
      "mgmt-ipv6-address": "3fff:172:20:20::3",
      "mgmt-ipv6-prefix-length": 64,
      "mac-address": "",
      "labels": {
        "clab-mgmt-net-bridge": "br-34417ee0e937",
        "clab-node-group": "",
        "clab-node-kind": "linux",
        "clab-node-lab-dir": "/media/sf_Cilium/containerlab/clab-calico-vxlan/host-external",
        "clab-node-longname": "clab-calico-vxlan-host-external",
        "clab-node-name": "host-external",
        "clab-node-type": "",
        "clab-owner": "comnetsemu",
        "clab-topo-file": "/media/sf_Cilium/containerlab/topo.yaml",
        "containerlab": "calico-vxlan"
      },
      "port-bindings": [
      ]
    },
    "k01": {
      "index": "1",
      "shortname": "k01",
      "longname": "clab-calico-vxlan-k01",
      "fqdn": "k01.calico-vxlan.io",
      "group": "",
      "labdir": "/media/sf_Cilium/containerlab/clab-calico-vxlan/k01",
      "kind": "k8s-kind",
      "image": "",
      "mgmt-net": "",
      "mgmt-intf": "",
      "mgmt-ipv4-address": "172.18.0.2",
      "mgmt-ipv4-prefix-length": 16,
      "mgmt-ipv6-address": "fc00:f853:ccd:e793::2",
      "mgmt-ipv6-prefix-length": 64,
      "mac-address": "",
      "labels": {
        "clab-mgmt-net-bridge": "br-34417ee0e937",
        "clab-node-group": "",
        "clab-node-kind": "k8s-kind",
        "clab-node-lab-dir": "/media/sf_Cilium/containerlab/clab-calico-vxlan/k01",
        "clab-node-longname": "clab-calico-vxlan-k01",
        "clab-node-name": "k01",
        "clab-node-type": "",
        "clab-owner": "comnetsemu",
        "clab-topo-file": "/media/sf_Cilium/containerlab/topo.yaml",
        "containerlab": "calico-vxlan"
      },
      "port-bindings": [
      ]
    },
    "k01-control-plane": {
      "index": "2",
      "shortname": "k01-control-plane",
      "longname": "k01-control-plane",
      "fqdn": "k01-control-plane.calico-vxlan.io",
      "group": "",
      "labdir": "/media/sf_Cilium/containerlab/clab-calico-vxlan/k01-control-plane",
      "kind": "ext-container",
      "image": "",
      "mgmt-net": "",
      "mgmt-intf": "",
      "mgmt-ipv4-address": "172.18.0.3",
      "mgmt-ipv4-prefix-length": 16,
      "mgmt-ipv6-address": "fc00:f853:ccd:e793::3",
      "mgmt-ipv6-prefix-length": 64,
      "mac-address": "",
      "labels": {
        "clab-mgmt-net-bridge": "br-34417ee0e937",
        "clab-node-group": "",
        "clab-node-kind": "ext-container",
        "clab-node-lab-dir": "/media/sf_Cilium/containerlab/clab-calico-vxlan/k01-control-plane",
        "clab-node-longname": "k01-control-plane",
        "clab-node-name": "k01-control-plane",
        "clab-node-type": "",
        "clab-owner": "comnetsemu",
        "clab-topo-file": "/media/sf_Cilium/containerlab/topo.yaml",
        "containerlab": "calico-vxlan"
      },
      "port-bindings": [
        {
          "host-ip": "127.0.0.1",
          "host-port": 36253,
          "port": 6443,
          "protocol": "tcp"
        }
      ]
    },
    "k01-worker": {
      "index": "3",
      "shortname": "k01-worker",
      "longname": "k01-worker",
      "fqdn": "k01-worker.calico-vxlan.io",
      "group": "",
      "labdir": "/media/sf_Cilium/containerlab/clab-calico-vxlan/k01-worker",
      "kind": "ext-container",
      "image": "",
      "mgmt-net": "",
      "mgmt-intf": "",
      "mgmt-ipv4-address": "172.18.0.2",
      "mgmt-ipv4-prefix-length": 16,
      "mgmt-ipv6-address": "fc00:f853:ccd:e793::2",
      "mgmt-ipv6-prefix-length": 64,
      "mac-address": "",
      "labels": {
        "clab-mgmt-net-bridge": "br-34417ee0e937",
        "clab-node-group": "",
        "clab-node-kind": "ext-container",
        "clab-node-lab-dir": "/media/sf_Cilium/containerlab/clab-calico-vxlan/k01-worker",
        "clab-node-longname": "k01-worker",
        "clab-node-name": "k01-worker",
        "clab-node-type": "",
        "clab-owner": "comnetsemu",
        "clab-topo-file": "/media/sf_Cilium/containerlab/topo.yaml",
        "containerlab": "calico-vxlan"
      },
      "port-bindings": [
      ]
    },
    "k01-worker2": {
      "index": "4",
      "shortname": "k01-worker2",
      "longname": "k01-worker2",
      "fqdn": "k01-worker2.calico-vxlan.io",
      "group": "",
      "labdir": "/media/sf_Cilium/containerlab/clab-calico-vxlan/k01-worker2",
      "kind": "ext-container",
      "image": "",
      "mgmt-net": "",
      "mgmt-intf": "",
      "mgmt-ipv4-address": "172.18.0.4",
      "mgmt-ipv4-prefix-length": 16,
      "mgmt-ipv6-address": "fc00:f853:ccd:e793::4",
      "mgmt-ipv6-prefix-length": 64,
      "mac-address": "",
      "labels": {
        "clab-mgmt-net-bridge": "br-34417ee0e937",
        "clab-node-group": "",
        "clab-node-kind": "ext-container",
        "clab-node-lab-dir": "/media/sf_Cilium/containerlab/clab-calico-vxlan/k01-worker2",
        "clab-node-longname": "k01-worker2",
        "clab-node-name": "k01-worker2",
        "clab-node-type": "",
        "clab-owner": "comnetsemu",
        "clab-topo-file": "/media/sf_Cilium/containerlab/topo.yaml",
        "containerlab": "calico-vxlan"
      },
      "port-bindings": [
      ]
    },
    "r0": {
      "index": "5",
      "shortname": "r0",
      "longname": "clab-calico-vxlan-r0",
      "fqdn": "r0.calico-vxlan.io",
      "group": "",
      "labdir": "/media/sf_Cilium/containerlab/clab-calico-vxlan/r0",
      "kind": "linux",
      "image": "frrouting/frr:v8.4.0",
      "mgmt-net": "",
      "mgmt-intf": "",
      "mgmt-ipv4-address": "172.20.20.2",
      "mgmt-ipv4-prefix-length": 24,
      "mgmt-ipv6-address": "3fff:172:20:20::2",
      "mgmt-ipv6-prefix-length": 64,
      "mac-address": "",
      "labels": {
        "clab-mgmt-net-bridge": "br-34417ee0e937",
        "clab-node-group": "",
        "clab-node-kind": "linux",
        "clab-node-lab-dir": "/media/sf_Cilium/containerlab/clab-calico-vxlan/r0",
        "clab-node-longname": "clab-calico-vxlan-r0",
        "clab-node-name": "r0",
        "clab-node-type": "",
        "clab-owner": "comnetsemu",
        "clab-topo-file": "/media/sf_Cilium/containerlab/topo.yaml",
        "containerlab": "calico-vxlan"
      },
      "port-bindings": [
      ]
    }
  },
  "links": [
    {
      "a": {
        "node": "r0",
        "interface": "net0",
        "mac": "aa:c1:ab:42:4f:19",
        "peer": "z"
      },
      "z": {
        "node": "k01-control-plane",
        "interface": "eth1",
        "mac": "aa:c1:ab:b8:bc:dc",
        "peer": "a"
      }
    },
    {
      "a": {
        "node": "r0",
        "interface": "net1",
        "mac": "aa:c1:ab:36:26:56",
        "peer": "z"
      },
      "z": {
        "node": "k01-worker",
        "interface": "eth1",
        "mac": "aa:c1:ab:3c:d8:92",
        "peer": "a"
      }
    },
    {
      "a": {
        "node": "r0",
        "interface": "net2",
        "mac": "aa:c1:ab:f0:87:fe",
        "peer": "z"
      },
      "z": {
        "node": "k01-worker2",
        "interface": "eth1",
        "mac": "aa:c1:ab:2a:58:dc",
        "peer": "a"
      }
    },
    {
      "a": {
        "node": "r0",
        "interface": "net3",
        "mac": "aa:c1:ab:cb:be:f1",
        "peer": "z"
      },
      "z": {
        "node": "host-external",
        "interface": "eth1",
        "mac": "aa:c1:ab:8a:94:15",
        "peer": "a"
      }
    }
  ]
}
